lightgbm/__init__.py
lightgbm/basic.py
lightgbm/callback.py
lightgbm/compat.py
lightgbm/dask.py
lightgbm/engine.py
lightgbm/lib_custom_parser.so
lightgbm/lib_lightgbm.so
lightgbm/lib_transform.so
lightgbm/libpath.py
lightgbm/plotting.py
lightgbm/sklearn.py
lightgbm_transform-3.3.2.post1.dist-info/METADATA
lightgbm_transform-3.3.2.post1.dist-info/WHEEL
lightgbm_transform-3.3.2.post1.dist-info/top_level.txt
lightgbm_transform-3.3.2.post1.dist-info/RECORD
