Metadata-Version: 2.1
Name: lightgbm-transform
Version: 3.3.2.post1
Summary: LightGBM feature transformation binding python package
Home-page: https://github.com/microsoft/lightgbm-transform
Maintainer: Jincheng Chen
Maintainer-email: chjinche@microsoft.com
License: The MIT License (Microsoft)
Platform: UNKNOWN
Classifier: Development Status :: 5 - Production/Stable
Classifier: Intended Audience :: Science/Research
Classifier: License :: OSI Approved :: MIT License
Classifier: Natural Language :: English
Classifier: Operating System :: MacOS
Classifier: Operating System :: Microsoft :: Windows
Classifier: Operating System :: POSIX
Classifier: Operating System :: Unix
Classifier: Programming Language :: Python :: 3
Classifier: Programming Language :: Python :: 3.6
Classifier: Programming Language :: Python :: 3.7
Classifier: Programming Language :: Python :: 3.8
Classifier: Programming Language :: Python :: 3.9
Classifier: Topic :: Scientific/Engineering :: Artificial Intelligence
Requires-Dist: wheel
Requires-Dist: numpy
Requires-Dist: scipy
Requires-Dist: scikit-learn (!=0.22.0)
Provides-Extra: dask
Requires-Dist: dask[array] (>=2.0.0) ; extra == 'dask'
Requires-Dist: dask[dataframe] (>=2.0.0) ; extra == 'dask'
Requires-Dist: dask[distributed] (>=2.0.0) ; extra == 'dask'
Requires-Dist: pandas ; extra == 'dask'
